requestgo/__init__.py
requestgo/core.py
requestgo/response.py
requestgo/utils.py
requestgo-0.1.0.dist-info/licenses/LICENSE
requestgo-0.1.0.dist-info/METADATA
requestgo-0.1.0.dist-info/WHEEL
requestgo-0.1.0.dist-info/top_level.txt
requestgo-0.1.0.dist-info/RECORD
